bigcodebench/__init__.py
bigcodebench/_version.py
bigcodebench/evaluate.py
bigcodebench/generate.py
bigcodebench/inspect.py
bigcodebench/sanitize.py
bigcodebench/syncheck.py
bigcodebench/data/__init__.py
bigcodebench/data/bigcodebench.py
bigcodebench/data/utils.py
bigcodebench/eval/__init__.py
bigcodebench/eval/_special_oracle.py
bigcodebench/eval/utils.py
bigcodebench/gen/__init__.py
bigcodebench/gen/util/__init__.py
bigcodebench/gen/util/anthropic_request.py
bigcodebench/gen/util/google_request.py
bigcodebench/gen/util/hf_inference_request.py
bigcodebench/gen/util/mistral_request.py
bigcodebench/gen/util/openai_request.py
bigcodebench/provider/__init__.py
bigcodebench/provider/anthropic.py
bigcodebench/provider/base.py
bigcodebench/provider/google.py
bigcodebench/provider/hf.py
bigcodebench/provider/hf_inference.py
bigcodebench/provider/mistral.py
bigcodebench/provider/openai.py
bigcodebench/provider/utility.py
bigcodebench/provider/vllm.py
bigcodebench-0.2.5.dist-info/licenses/LICENSE
bigcodebench-0.2.5.dist-info/METADATA
bigcodebench-0.2.5.dist-info/WHEEL
bigcodebench-0.2.5.dist-info/entry_points.txt
bigcodebench-0.2.5.dist-info/top_level.txt
bigcodebench-0.2.5.dist-info/RECORD
