Metadata-Version: 2.4
Name: bigcodebench
Version: 0.2.5
Summary: "Evaluation package for BigCodeBench"
Home-page: https://github.com/bigcode-project/bigcodebench
License: Apache-2.0
Platform: any
Classifier: Operating System :: OS Independent
Classifier: Programming Language :: Python :: 3
Classifier: License :: OSI Approved :: Apache Software License
Requires-Python: >=3.8
License-File: LICENSE
Requires-Dist: appdirs>=1.4.4
Requires-Dist: fire>=0.6.0
Requires-Dist: multipledispatch>=0.6.0
Requires-Dist: pqdm>=0.2.0
Requires-Dist: tempdir>=0.7.1
Requires-Dist: termcolor>=2.0.0
Requires-Dist: tqdm>=4.56.0
Requires-Dist: tree_sitter>=0.22.0
Requires-Dist: tree-sitter-python>=0.21.0
Requires-Dist: wget>=3.2
Requires-Dist: transformers
Requires-Dist: datasets
Requires-Dist: gradio-client
Requires-Dist: vllm
Requires-Dist: numpy
Requires-Dist: rich
Requires-Dist: accelerate>=0.30.1
Requires-Dist: anthropic>=0.26.1
Requires-Dist: google-genai
Requires-Dist: mistralai<1.0.0,>=0.2.0
Requires-Dist: openai>=1.11.1
Requires-Dist: e2b
Dynamic: license-file
